pyvectorguidance/VectorGuidance.py
pyvectorguidance/__init__.py
pyvectorguidance-1.0.3.dist-info/LICENSE
pyvectorguidance-1.0.3.dist-info/METADATA
pyvectorguidance-1.0.3.dist-info/WHEEL
pyvectorguidance-1.0.3.dist-info/top_level.txt
pyvectorguidance-1.0.3.dist-info/RECORD
